nqueenplay/__init__.py
nqueenplay/exceptions.py
nqueenplay/move_direction.py
nqueenplay/queens.py
nqueenplay/version.py
nqueenplay-0.0.6.dist-info/LICENSE
nqueenplay-0.0.6.dist-info/METADATA
nqueenplay-0.0.6.dist-info/WHEEL
nqueenplay-0.0.6.dist-info/top_level.txt
nqueenplay-0.0.6.dist-info/RECORD
