Metadata-Version: 2.1
Name: nqueenplay
Version: 0.0.6
Summary: N-Queens puzzle player. This tool will generate randomly or randomly locked puzzle, you may use this as "a boxing bag" to practice problem solving algorithm.
Home-page: https://github.com/eiproject/nqueenplay
Author: eiproject
Author-email: razifrizqullah@gmail.com
License: MIT
Keywords: n-queens,nqueens,puzzle
Platform: UNKNOWN
Classifier: Development Status :: 5 - Production/Stable
Classifier: Intended Audience :: Developers
Classifier: Intended Audience :: Education
Classifier: Intended Audience :: Science/Research
Classifier: Programming Language :: Python :: 3 :: Only
Classifier: Operating System :: Unix
Classifier: Operating System :: MacOS :: MacOS X
Classifier: Operating System :: Microsoft :: Windows
Classifier: License :: OSI Approved :: MIT License
